{
    "version": "12980",
    "description": "Secure, Fast & Private Web Browser with Adblocker",
    "homepage": "https://brave.com",
    "license": {
        "identifier": "MPL 2.0",
        "url": "https://github.com/brave/brave-browser/blob/master/LICENSE"
    },
    "architecture": {
        "64bit": {
            "url": "https://brave-browser-downloads.s3.brave.com/latest/brave_installer-x64.exe#/dl.7z",
            "hash": "dd5b344b6c2acf158f0aef101e1fd11ef30fd0bd691b65c5bf85f1eebbdfb287"
        },
        "32bit": {
            "url": "https://brave-browser-downloads.s3.brave.com/latest/brave_installer-ia32.exe#/dl.7z",
            "hash": "d1356d68f589aea16d1376d6946dea41ebf54e5d7a743dc24a5f6755452012f9"
        }
    },
    "pre_install": "Expand-7zipArchive \"$dir\\chrome.7z\" -ExtractDir 'Chrome-bin' -Removal",
    "bin": "brave.exe",
    "shortcuts": [
        [
            "brave.exe",
            "Brave"
        ]
    ],
    "checkver": {
        "url": "https://brave.com/latest/",
        "regex": "release-notes-v([\\d]+)"
    },
    "autoupdate": {
        "architecture": {
            "64bit": {
                "url": "https://brave-browser-downloads.s3.brave.com/latest/brave_installer-x64.exe#/dl.7z"
            },
            "32bit": {
                "url": "https://brave-browser-downloads.s3.brave.com/latest/brave_installer-ia32.exe#/dl.7z"
            }
        }
    }
}
